pandas_src_cleaning/__init__.py
pandas_src_cleaning/categorical_encoder.py
pandas_src_cleaning/data_type_converter.py
pandas_src_cleaning/date_time_handler.py
pandas_src_cleaning/feature_engineer.py
pandas_src_cleaning/missing_value_handler.py
pandas_src_cleaning/outlier_handler.py
pandas_src_cleaning/scaler.py
pandas_src_cleaning/text_cleaner.py
src/__init__.py
src/categorical_encoder.py
src/data_type_converter.py
src/date_time_handler.py
src/feature_engineer.py
src/missing_value_handler.py
src/outlier_handler.py
src/scaler.py
src/text_cleaner.py
test/__init__.py
pandas_src_cleaning-0.1.1.dist-info/LICENSE
pandas_src_cleaning-0.1.1.dist-info/METADATA
pandas_src_cleaning-0.1.1.dist-info/WHEEL
pandas_src_cleaning-0.1.1.dist-info/top_level.txt
pandas_src_cleaning-0.1.1.dist-info/RECORD
