Metadata-Version: 2.1
Name: pandas_src_cleaning
Version: 0.1.1
Summary: A comprehensive Python library for data preprocessing and cleaning
Home-page: https://github.com/MuratKeskin0/Term_Project_Python_Data_Cleaning
Author: Murat Keskin & Ahmet Bagbakan & Cagla Ilhani
Author-email: eng.murat.keskin@gmail.com
Classifier: Programming Language :: Python :: 3
Classifier: License :: OSI Approved :: MIT License
Classifier: Operating System :: OS Independent
Requires-Python: >=3.6
License-File: LICENSE
Requires-Dist: pandas
Requires-Dist: numpyscikit-learn
Requires-Dist: nltk
